{
    "gridPropsList": [
        {
            "divClassName": "w3-third",
            "column": [
                {
                    "href": "http://rashtell.com/barcut/barcut/index.html",
                    "imgSrc": "http://rashtell.com/barcut/barcut/img/about-img2.jpg",
                    "imgStyle": {
                        "width": "100%"
                    }
                },
                {
                    "href": "http://rashtell.com/beckham/beckham/index.html",
                    "imgSrc": "http://rashtell.com/beckham/beckham/images/author-1.jpg",
                    "imgStyle": {
                        "width": "100%"
                    }
                },
                {
                    "href": "http://rashtell.com/MobApp/MobApp/index.html",
                    "imgSrc": "http://rashtell.com/MobApp/MobApp/images/dualphone.png",
                    "imgStyle": {
                        "width": "100%"
                    }
                }
            ]
        },
        {
            "divClassName": "w3-third",
            "column": [
                {
                    "href": "http://rashtell.com/MyPortfolio/index.html",
                    "imgSrc": "http://rashtell.com/MyPortfolio/images/header-bg1.jpg",
                    "imgStyle": {
                        "width": "100%"
                    }
                },
                {
                    "href": "http://rashtell.com/Personal/thebootstrapthemes-personal/index.html",
                    "imgSrc": "http://rashtell.com/Personal/thebootstrapthemes-personal/images/back.jpg",
                    "imgStyle": {
                        "width": "100%"
                    }
                },
                {
                    "href": "http://rashtell.com/po-portfolio/po-portfolio/index.html",
                    "imgSrc": "http://rashtell.com/po-portfolio/po-portfolio/images/1.jpg",
                    "imgStyle": {
                        "width": "100%"
                    }
                }
            ]
        },
        {
            "divClassName": "w3-third",
            "column": [
                {
                    "href": "http://rashtell.com/politics/politics/index.html",
                    "imgSrc": "http://rashtell.com/politics/politics/img/video-bg.jpg",
                    "imgStyle": {
                        "width": "100%"
                    }
                },
                {
                    "href": "http://rashtell.com/portfolio/portfolio/index.html",
                    "imgSrc": "http://rashtell.com/portfolio/portfolio/img/header-bg.jpg",
                    "imgStyle": {
                        "width": "100%"
                    }
                },
                {
                    "href": "http://rashtell.com/ProFolio/profolio/index.html",
                    "imgSrc": "http://rashtell.com/ProFolio/profolio/images/1.jpg",
                    "imgStyle": {
                        "width": "100%"
                    }
                }
            ]
        }
    ]
}